{
  "announcement_id": 5,
  "housing_info": [
    {
      "name": "T&K신림1",
      "address": "조원중앙로59-3, 신림동1649-11, 12",
      "district": "관악구",
      "total_households": null,
      "supply_households": [
        "10호",
        "5호"
      ],
      "type": [
        "도시형생활주택 (분리형원룸)",
        "도시형생활주택 (2룸)"
      ],
      "house_type": [
        "29A",
        "45C"
      ],
      "elevator": true,
      "parking": "자주식(지상)"
    },
    {
      "name": "경호빌",
      "address": "조원로16가길41, 신림동537-14",
      "district": "관악구",
      "total_households": null,
      "supply_households": [
        "13호",
        "2호"
      ],
      "type": [
        "도시형생활주택 (개방형원룸)",
        "도시형생활주택 (분리형원룸)"
      ],
      "house_type": [
        "28B",
        "43A"
      ],
      "elevator": true,
      "parking": "자주식(지상)"
    },
    {
      "name": "오류동청년주택",
      "address": "경인로27길13, 오류동31-121",
      "district": "구로구",
      "total_households": null,
      "supply_households": [
        "88호"
      ],
      "type": [
        "오피스텔 (개방형원룸)"
      ],
      "house_type": [
        "28B"
      ],
      "elevator": true,
      "parking": "자주식(지상,지하)/ 기계식(지하)"
    },
    {
      "name": "하늘사랑채7차",
      "address": "안양천로537가길18-8, 고척동62-85",
      "district": "구로구",
      "total_households": null,
      "supply_households": [
        "14호",
        "1호"
      ],
      "type": [
        "도시형생활주택 (개방형원룸)",
        "도시형생활주택 (분리형원룸)"
      ],
      "house_type": [
        "19B",
        "30A"
      ],
      "elevator": false,
      "parking": "자주식(지상)"
    },
    {
      "name": "청정마을",
      "address": "가마산로20나길23,구로동429-254",
      "district": "구로구",
      "total_households": null,
      "supply_households": [
        "1호",
        "8호"
      ],
      "type": [
        "도시형생활주택 (개방형원룸)",
        "도시형생활주택 (분리형원룸)"
      ],
      "house_type": [
        "26B",
        "36A"
      ],
      "elevator": true,
      "parking": "자주식(지상)"
    },
    {
      "name": "한별#3",
      "address": "두산로10길9, 독산동330-13",
      "district": "금천구",
      "total_households": null,
      "supply_households": [
        "4호"
      ],
      "type": [
        "오피스텔 (분리형원룸)"
      ],
      "house_type": [
        "28A"
      ],
      "elevator": true,
      "parking": "자주식(지상)/ 기계식(지상,지하)"
    },
    {
      "name": "스타힐스",
      "address": "독산로23길19, 시흥동840-34, 89",
      "district": "금천구",
      "total_households": null,
      "supply_households": [
        "2호",
        "13호"
      ],
      "type": [
        "도시형생활주택 (개방형원룸)",
        "도시형생활주택 (분리형원룸)"
      ],
      "house_type": [
        "28B",
        "30A"
      ],
      "elevator": true,
      "parking": "자주식(지상)"
    }
  ]
}